tailslide/__init__.py
tailslide/mongoengine/__init__.py
tailslide-0.2.0.dist-info/LICENSE.txt
tailslide-0.2.0.dist-info/METADATA
tailslide-0.2.0.dist-info/WHEEL
tailslide-0.2.0.dist-info/top_level.txt
tailslide-0.2.0.dist-info/RECORD
