Metadata-Version: 2.1
Name: tailslide
Version: 0.2.0
Summary: Median and percentile for Django and MongoEngine
Home-page: https://github.com/ankane/tailslide
Author: Andrew Kane
Author-email: andrew@ankane.org
License: MIT
Requires-Python: >=3.8
License-File: LICENSE.txt
